Topsis_Vaibhav_102083059/__init__.py
Topsis_Vaibhav_102083059/topsis.py
Topsis_Vaibhav_102083059-0.0.3.dist-info/LICENSE
Topsis_Vaibhav_102083059-0.0.3.dist-info/METADATA
Topsis_Vaibhav_102083059-0.0.3.dist-info/WHEEL
Topsis_Vaibhav_102083059-0.0.3.dist-info/top_level.txt
Topsis_Vaibhav_102083059-0.0.3.dist-info/RECORD
