Metadata-Version: 2.1
Name: Topsis-Vaibhav-102083059
Version: 0.0.3
Summary: A package which generates a csv file containing topsis scores and ranks.
Author: Vaibhav Mukhi
Author-email: mukhivaibhav4@gmail.com
License: UNKNOWN
Keywords: python,Topsis,Topsis Package,Topsis Libraray,Vaibhav
Platform: UNKNOWN
Classifier: Development Status :: 4 - Beta
Classifier: Intended Audience :: Developers
Classifier: Programming Language :: Python :: 3
Classifier: Operating System :: Unix
Classifier: Operating System :: MacOS :: MacOS X
Classifier: Operating System :: Microsoft :: Windows
License-File: LICENSE
